guispark/__init__.py
guispark-0.0.2.dist-info/licenses/LICENSE.txt
guispark-0.0.2.dist-info/METADATA
guispark-0.0.2.dist-info/WHEEL
guispark-0.0.2.dist-info/top_level.txt
guispark-0.0.2.dist-info/RECORD
